pcapana-0.1.4.dist-info/licenses/LICENSE
pcapanalyzer/__init__.py
pcapanalyzer/cli.py
pcapanalyzer/services/__init__.py
pcapanalyzer/services/bandwidth_usage.py
pcapanalyzer/services/osi_analyzer.py
pcapanalyzer/services/pcap_parser.py
pcapanalyzer/services/port_analyzer.py
pcapanalyzer/services/protocol_stats.py
pcapanalyzer/services/report_generator.py
pcapanalyzer/services/visited_domains.py
pcapana-0.1.4.dist-info/METADATA
pcapana-0.1.4.dist-info/WHEEL
pcapana-0.1.4.dist-info/entry_points.txt
pcapana-0.1.4.dist-info/top_level.txt
pcapana-0.1.4.dist-info/RECORD
