Metadata-Version: 2.4
Name: pcapana
Version: 0.1.4
Summary: A command-line tool to analyze PCAP files for Protocol Statistics, Visited Domains, OSI Layer Analysis, Bandwidth Analysis & Port Analysis with the option to export it as a HTML report
Author: Harsh M Shah
License: MIT
Project-URL: Homepage, https://github.com/12hms12/pcapana
Project-URL: Repository, https://github.com/12hms12/pcapana
Project-URL: Issues, https://github.com/12hms12/pcapana/issues
Project-URL: PyPI, https://pypi.org/project/pcapana/
Requires-Python: >=3.7
License-File: LICENSE
Requires-Dist: pyshark
Dynamic: license-file
